Rendu VLSI/VHDL pour simulation/adder.vhdl
LIBRARY IEEE;
use IEEE.std_logic_1164.all;
use IEEE.numeric_std.all;


ENTITY fulladd is
    PORT(
        a, b, cin : IN std_logic;
        r, cout : OUT std_logic);
end ENTITY;

ARCHITECTURE mon_fulladd of fulladd is
    BEGIN
    r <= (a xor b) xor cin;
    cout <= ((a xor b) and cin ) or (a and b);
END mon_fulladd;

LIBRARY IEEE;
use IEEE.std_logic_1164.all;
use IEEE.numeric_std.all;


ENTITY add4bit is
    PORT(
        x : IN std_logic_vector(3 downto 0);
        y : IN std_logic_vector (3 downto 0);
        cin : IN std_logic;
        cout : OUT std_logic;
        r : OUT std_logic_vector (3 downto 0)
    );

end entity;

architecture mon_add4bit of add4bit is

    component fulladd is
        port (
            signal a : in std_logic;
            signal b : in std_logic;
            signal cin : in std_logic;
            signal r : out std_logic;
            signal cout : out std_logic
            );
    END component;
    signal c1,c2,c3 : std_logic;
    
    begin

    fa0 : component fulladd 
        port map (
            a => x(0),
            b => y(0),
            cin => cin,
            r => r(0),
            cout => c1
        );

    fa1 : component fulladd 
        port map (
            a => x(1),
            b => y(1),
            cin => c1,
            r => r(1),
            cout => c2
        );
    fa2 : component fulladd 
        port map (
            a => x(2),
            b => y(2),
            cin => c2,
            r => r(2),
            cout => c3
        );
    fa3 : component fulladd 
        port map (
            a => x(3),
            b => y(3),
            cin => c3,
            r => r(3),
            cout => cout
        );

end architecture;

TME1/adder_tb.vhdl
library ieee;
use ieee.std_logic_1164.all;
use ieee.numeric_std.all;

entity adder_tb is
end entity;

architecture tb of adder_tb is
component add4bit
  port(
    x : IN std_logic_vector(3 downto 0);
    y : IN std_logic_vector (3 downto 0);
    cin : IN std_logic;
    cout : OUT std_logic;
    r : OUT std_logic_vector (3 downto 0)
);
end component;

signal tb_cin : std_logic;
signal tb_argument_x: std_logic_vector(3 downto 0);
signal tb_argument_y : std_logic_vector(3 downto 0);
signal tb_result: std_logic_vector(3 downto 0);
signal tb_cout : std_logic;
begin

U1: add4bit port map(tb_argument_x,tb_argument_y,tb_cin,tb_cout,tb_result);

process


begin
    tb_cin<='0';
    for i in 0 to 15 loop
        for j in 0 to 15 loop
            tb_argument_x <= std_logic_vector(to_unsigned(i,4));
            tb_argument_y <= std_logic_vector(to_unsigned(j,4));
            

            wait for 2 ns;

        end loop;
    end loop;

    -- Start computation
  tb_argument_x <= "1111";
  tb_argument_y <= "0000";
  tb_cin <= '0';

  wait for 10 ns;

  tb_argument_x <= "1010";
  tb_argument_y <= "0101";
  tb_cin <= '0';


  wait for 10 ns;

  tb_argument_x <= "1001";
  tb_argument_y <= "0011";
  tb_cin <= '0';

  wait for 10 ns;

  wait;
end process;

end architecture;

TME1/adder.vcd
$date
  Wed Oct 11 11:03:47 2023
$end
$version
  GHDL v0
$end
$timescale
  1 fs
$end
$scope module standard $end
$upscope $end
$scope module std_logic_1164 $end
$upscope $end
$scope module numeric_std $end
$upscope $end
$scope module adder_tb $end
$var reg 1 ! tb_cin $end
$var reg 4 " tb_argument_x[3:0] $end
$var reg 4 # tb_argument_y[3:0] $end
$var reg 4 $ tb_result[3:0] $end
$var reg 1 % tb_cout $end
$scope module u1 $end
$var reg 4 & x[3:0] $end
$var reg 4 ' y[3:0] $end
$var reg 1 ( cin $end
$var reg 1 ) cout $end
$var reg 4 * r[3:0] $end
$var reg 1 + c1 $end
$var reg 1 , c2 $end
$var reg 1 - c3 $end
$scope module fa0 $end
$var reg 1 . a $end
$var reg 1 / b $end
$var reg 1 0 cin $end
$var reg 1 1 r $end
$var reg 1 2 cout $end
$upscope $end
$scope module fa1 $end
$var reg 1 3 a $end
$var reg 1 4 b $end
$var reg 1 5 cin $end
$var reg 1 6 r $end
$var reg 1 7 cout $end
$upscope $end
$scope module fa2 $end
$var reg 1 8 a $end
$var reg 1 9 b $end
$var reg 1 : cin $end
$var reg 1 ; r $end
$var reg 1 < cout $end
$upscope $end
$scope module fa3 $end
$var reg 1 = a $end
$var reg 1 > b $end
$var reg 1 ? cin $end
$var reg 1 @ r $end
$var reg 1 A cout $end
$upscope $end
$upscope $end
$upscope $end
$enddefinitions $end
#0
0!
b0000 "
b0000 #
b0000 $
0%
b0000 &
b0000 '
0(
0)
b0000 *
0+
0,
0-
0.
0/
00
01
02
03
04
05
06
07
08
09
0:
0;
0<
0=
0>
0?
0@
0A
#2000000
b0001 #
b0001 $
b0001 '
b0001 *
1/
11
#4000000
b0010 #
b0010 $
b0010 '
b0010 *
0/
01
14
16
#6000000
b0011 #
b0011 $
b0011 '
b0011 *
1/
11
#8000000
b0100 #
b0100 $
b0100 '
b0100 *
0/
01
04
06
19
1;
#10000000
b0101 #
b0101 $
b0101 '
b0101 *
1/
11
#12000000
b0110 #
b0110 $
b0110 '
b0110 *
0/
01
14
16
#14000000
b0111 #
b0111 $
b0111 '
b0111 *
1/
11
#16000000
b1000 #
b1000 $
b1000 '
b1000 *
0/
01
04
06
09
0;
1>
1@
#18000000
b1001 #
b1001 $
b1001 '
b1001 *
1/
11
#20000000
b1010 #
b1010 $
b1010 '
b1010 *
0/
01
14
16
#22000000
b1011 #
b1011 $
b1011 '
b1011 *
1/
11
#24000000
b1100 #
b1100 $
b1100 '
b1100 *
0/
01
04
06
19
1;
#26000000
b1101 #
b1101 $
b1101 '
b1101 *
1/
11
#28000000
b1110 #
b1110 $
b1110 '
b1110 *
0/
01
14
16
#30000000
b1111 #
b1111 $
b1111 '
b1111 *
1/
11
#32000000
b0001 "
b0000 #
b0001 $
b0001 &
b0000 '
b0001 *
1.
0/
04
06
09
0;
0>
0@
#34000000
b0001 #
b0010 $
b0001 '
b0010 *
1+
1/
01
12
15
16
#36000000
b0010 #
b0011 $
b0010 '
b0011 *
0+
0,
0/
11
02
14
05
16
07
0:
0;
#38000000
b0011 #
b0100 $
b0011 '
b0100 *
1+
1,
1/
01
12
15
06
17
1:
1;
#40000000
b0100 #
b0101 $
b0100 '
b0101 *
0+
0,
0-
0/
11
02
04
05
06
07
19
0:
1;
0<
0?
0@
#42000000
b0101 #
b0110 $
b0101 '
b0110 *
1+
1/
01
12
15
16
#44000000
b0110 #
b0111 $
b0110 '
b0111 *
0+
0,
0-
0/
11
02
14
05
16
07
0:
1;
0<
0?
0@
#46000000
b0111 #
b1000 $
b0111 '
b1000 *
1+
1,
1-
1/
01
12
15
06
17
1:
0;
1<
1?
1@
#48000000
b1000 #
b1001 $
0%
b1000 '
0)
b1001 *
0+
0,
0-
0/
11
02
04
05
06
07
09
0:
0;
0<
1>
0?
1@
0A
#50000000
b1001 #
b1010 $
b1001 '
b1010 *
1+
1/
01
12
15
16
#52000000
b1010 #
b1011 $
b1010 '
b1011 *
0+
0,
0/
11
02
14
05
16
07
0:
0;
#54000000
b1011 #
b1100 $
b1011 '
b1100 *
1+
1,
1/
01
12
15
06
17
1:
1;
#56000000
b1100 #
b1101 $
0%
b1100 '
0)
b1101 *
0+
0,
0-
0/
11
02
04
05
06
07
19
0:
1;
0<
0?
1@
0A
#58000000
b1101 #
b1110 $
b1101 '
b1110 *
1+
1/
01
12
15
16
#60000000
b1110 #
b1111 $
0%
b1110 '
0)
b1111 *
0+
0,
0-
0/
11
02
14
05
16
07
0:
1;
0<
0?
1@
0A
#62000000
b1111 #
b0000 $
1%
b1111 '
1)
b0000 *
1+
1,
1-
1/
01
12
15
06
17
1:
0;
1<
1?
0@
1A
#64000000
b0010 "
b0000 #
b0010 $
0%
b0010 &
b0000 '
0)
b0010 *
0+
0,
0-
0.
0/
02
13
04
05
16
07
09
0:
0;
0<
0>
0?
0@
0A
#66000000
b0001 #
b0011 $
b0001 '
b0011 *
1/
11
#68000000
b0010 #
b0100 $
b0010 '
b0100 *
1,
0/
01
14
06
17
1:
1;
#70000000
b0011 #
b0101 $
b0011 '
b0101 *
1/
11
#72000000
b0100 #
b0110 $
b0100 '
b0110 *
0,
0-
0/
01
04
16
07
19
0:
1;
0<
0?
0@
#74000000
b0101 #
b0111 $
b0101 '
b0111 *
1/
11
#76000000
b0110 #
b1000 $
b0110 '
b1000 *
1,
1-
0/
01
14
06
17
1:
0;
1<
1?
1@
#78000000
b0111 #
b1001 $
b0111 '
b1001 *
1/
11
#80000000
b1000 #
b1010 $
0%
b1000 '
0)
b1010 *
0,
0-
0/
01
04
16
07
09
0:
0;
0<
1>
0?
1@
0A
#82000000
b1001 #
b1011 $
b1001 '
b1011 *
1/
11
#84000000
b1010 #
b1100 $
b1010 '
b1100 *
1,
0/
01
14
06
17
1:
1;
#86000000
b1011 #
b1101 $
b1011 '
b1101 *
1/
11
#88000000
b1100 #
b1110 $
0%
b1100 '
0)
b1110 *
0,
0-
0/
01
04
16
07
19
0:
1;
0<
0?
1@
0A
#90000000
b1101 #
b1111 $
b1101 '
b1111 *
1/
11
#92000000
b1110 #
b0000 $
1%
b1110 '
1)
b0000 *
1,
1-
0/
01
14
06
17
1:
0;
1<
1?
0@
1A
#94000000
b1111 #
b0001 $
b1111 '
b0001 *
1/
11
#96000000
b0011 "
b0000 #
b0011 $
0%
b0011 &
b0000 '
0)
b0011 *
0,
0-
1.
0/
04
16
07
09
0:
0;
0<
0>
0?
0@
0A
#98000000
b0001 #
b0100 $
b0001 '
b0100 *
1+
1,
1/
01
12
15
06
17
1:
1;
#100000000
b0010 #
b0101 $
b0010 '
b0101 *
0+
0/
11
02
14
05
06
#102000000
b0011 #
b0110 $
b0011 '
b0110 *
1+
1/
01
12
15
16
#104000000
b0100 #
b0111 $
b0100 '
b0111 *
0+
0,
0-
0/
11
02
04
05
16
07
19
0:
1;
0<
0?
0@
#106000000
b0101 #
b1000 $
b0101 '
b1000 *
1+
1,
1-
1/
01
12
15
06
17
1:
0;
1<
1?
1@
#108000000
b0110 #
b1001 $
b0110 '
b1001 *
0+
0/
11
02
14
05
06
#110000000
b0111 #
b1010 $
b0111 '
b1010 *
1+
1/
01
12
15
16
#112000000
b1000 #
b1011 $
0%
b1000 '
0)
b1011 *
0+
0,
0-
0/
11
02
04
05
16
07
09
0:
0;
0<
1>
0?
1@
0A
#114000000
b1001 #
b1100 $
b1001 '
b1100 *
1+
1,
1/
01
12
15
06
17
1:
1;
#116000000
b1010 #
b1101 $
b1010 '
b1101 *
0+
0/
11
02
14
05
06
#118000000
b1011 #
b1110 $
b1011 '
b1110 *
1+
1/
01
12
15
16
#120000000
b1100 #
b1111 $
0%
b1100 '
0)
b1111 *
0+
0,
0-
0/
11
02
04
05
16
07
19
0:
1;
0<
0?
1@
0A
#122000000
b1101 #
b0000 $
1%
b1101 '
1)
b0000 *
1+
1,
1-
1/
01
12
15
06
17
1:
0;
1<
1?
0@
1A
#124000000
b1110 #
b0001 $
b1110 '
b0001 *
0+
0/
11
02
14
05
06
#126000000
b1111 #
b0010 $
b1111 '
b0010 *
1+
1/
01
12
15
16
#128000000
b0100 "
b0000 #
b0100 $
0%
b0100 &
b0000 '
0)
b0100 *
0+
0,
0-
0.
0/
02
03
04
05
06
07
18
09
0:
1;
0<
0>
0?
0@
0A
#130000000
b0001 #
b0101 $
b0001 '
b0101 *
1/
11
#132000000
b0010 #
b0110 $
b0010 '
b0110 *
0/
01
14
16
#134000000
b0011 #
b0111 $
b0011 '
b0111 *
1/
11
#136000000
b0100 #
b1000 $
b0100 '
b1000 *
1-
0/
01
04
06
19
0;
1<
1?
1@
#138000000
b0101 #
b1001 $
b0101 '
b1001 *
1/
11
#140000000
b0110 #
b1010 $
b0110 '
b1010 *
0/
01
14
16
#142000000
b0111 #
b1011 $
b0111 '
b1011 *
1/
11
#144000000
b1000 #
b1100 $
0%
b1000 '
0)
b1100 *
0-
0/
01
04
06
09
1;
0<
1>
0?
1@
0A
#146000000
b1001 #
b1101 $
b1001 '
b1101 *
1/
11
#148000000
b1010 #
b1110 $
b1010 '
b1110 *
0/
01
14
16
#150000000
b1011 #
b1111 $
b1011 '
b1111 *
1/
11
#152000000
b1100 #
b0000 $
1%
b1100 '
1)
b0000 *
1-
0/
01
04
06
19
0;
1<
1?
0@
1A
#154000000
b1101 #
b0001 $
b1101 '
b0001 *
1/
11
#156000000
b1110 #
b0010 $
b1110 '
b0010 *
0/
01
14
16
#158000000
b1111 #
b0011 $
b1111 '
b0011 *
1/
11
#160000000
b0101 "
b0000 #
b0101 $
0%
b0101 &
b0000 '
0)
b0101 *
0-
1.
0/
04
06
09
1;
0<
0>
0?
0@
0A
#162000000
b0001 #
b0110 $
b0001 '
b0110 *
1+
1/
01
12
15
16
#164000000
b0010 #
b0111 $
b0010 '
b0111 *
0+
0,
0-
0/
11
02
14
05
16
07
0:
1;
0<
0?
0@
#166000000
b0011 #
b1000 $
b0011 '
b1000 *
1+
1,
1-
1/
01
12
15
06
17
1:
0;
1<
1?
1@
#168000000
b0100 #
b1001 $
b0100 '
b1001 *
0+
0,
0/
11
02
04
05
06
07
19
0:
0;
#170000000
b0101 #
b1010 $
b0101 '
b1010 *
1+
1/
01
12
15
16
#172000000
b0110 #
b1011 $
b0110 '
b1011 *
0+
0,
0/
11
02
14
05
16
07
0:
0;
#174000000
b0111 #
b1100 $
b0111 '
b1100 *
1+
1,
1/
01
12
15
06
17
1:
1;
#176000000
b1000 #
b1101 $
0%
b1000 '
0)
b1101 *
0+
0,
0-
0/
11
02
04
05
06
07
09
0:
1;
0<
1>
0?
1@
0A
#178000000
b1001 #
b1110 $
b1001 '
b1110 *
1+
1/
01
12
15
16
#180000000
b1010 #
b1111 $
0%
b1010 '
0)
b1111 *
0+
0,
0-
0/
11
02
14
05
16
07
0:
1;
0<
0?
1@
0A
#182000000
b1011 #
b0000 $
1%
b1011 '
1)
b0000 *
1+
1,
1-
1/
01
12
15
06
17
1:
0;
1<
1?
0@
1A
#184000000
b1100 #
b0001 $
b1100 '
b0001 *
0+
0,
0/
11
02
04
05
06
07
19
0:
0;
#186000000
b1101 #
b0010 $
b1101 '
b0010 *
1+
1/
01
12
15
16
#188000000
b1110 #
b0011 $
b1110 '
b0011 *
0+
0,
0/
11
02
14
05
16
07
0:
0;
#190000000
b1111 #
b0100 $
b1111 '
b0100 *
1+
1,
1/
01
12
15
06
17
1:
1;
#192000000
b0110 "
b0000 #
b0110 $
0%
b0110 &
b0000 '
0)
b0110 *
0+
0,
0-
0.
0/
02
13
04
05
16
07
09
0:
1;
0<
0>
0?
0@
0A
#194000000
b0001 #
b0111 $
b0001 '
b0111 *
1/
11
#196000000
b0010 #
b1000 $
b0010 '
b1000 *
1,
1-
0/
01
14
06
17
1:
0;
1<
1?
1@
#198000000
b0011 #
b1001 $
b0011 '
b1001 *
1/
11
#200000000
b0100 #
b1010 $
b0100 '
b1010 *
0,
0/
01
04
16
07
19
0:
0;
#202000000
b0101 #
b1011 $
b0101 '
b1011 *
1/
11
#204000000
b0110 #
b1100 $
b0110 '
b1100 *
1,
0/
01
14
06
17
1:
1;
#206000000
b0111 #
b1101 $
b0111 '
b1101 *
1/
11
#208000000
b1000 #
b1110 $
0%
b1000 '
0)
b1110 *
0,
0-
0/
01
04
16
07
09
0:
1;
0<
1>
0?
1@
0A
#210000000
b1001 #
b1111 $
b1001 '
b1111 *
1/
11
#212000000
b1010 #
b0000 $
1%
b1010 '
1)
b0000 *
1,
1-
0/
01
14
06
17
1:
0;
1<
1?
0@
1A
#214000000
b1011 #
b0001 $
b1011 '
b0001 *
1/
11
#216000000
b1100 #
b0010 $
b1100 '
b0010 *
0,
0/
01
04
16
07
19
0:
0;
#218000000
b1101 #
b0011 $
b1101 '
b0011 *
1/
11
#220000000
b1110 #
b0100 $
b1110 '
b0100 *
1,
0/
01
14
06
17
1:
1;
#222000000
b1111 #
b0101 $
b1111 '
b0101 *
1/
11
#224000000
b0111 "
b0000 #
b0111 $
0%
b0111 &
b0000 '
0)
b0111 *
0,
0-
1.
0/
04
16
07
09
0:
1;
0<
0>
0?
0@
0A
#226000000
b0001 #
b1000 $
b0001 '
b1000 *
1+
1,
1-
1/
01
12
15
06
17
1:
0;
1<
1?
1@
#228000000
b0010 #
b1001 $
b0010 '
b1001 *
0+
0/
11
02
14
05
06
#230000000
b0011 #
b1010 $
b0011 '
b1010 *
1+
1/
01
12
15
16
#232000000
b0100 #
b1011 $
b0100 '
b1011 *
0+
0,
0/
11
02
04
05
16
07
19
0:
0;
#234000000
b0101 #
b1100 $
b0101 '
b1100 *
1+
1,
1/
01
12
15
06
17
1:
1;
#236000000
b0110 #
b1101 $
b0110 '
b1101 *
0+
0/
11
02
14
05
06
#238000000
b0111 #
b1110 $
b0111 '
b1110 *
1+
1/
01
12
15
16
#240000000
b1000 #
b1111 $
0%
b1000 '
0)
b1111 *
0+
0,
0-
0/
11
02
04
05
16
07
09
0:
1;
0<
1>
0?
1@
0A
#242000000
b1001 #
b0000 $
1%
b1001 '
1)
b0000 *
1+
1,
1-
1/
01
12
15
06
17
1:
0;
1<
1?
0@
1A
#244000000
b1010 #
b0001 $
b1010 '
b0001 *
0+
0/
11
02
14
05
06
#246000000
b1011 #
b0010 $
b1011 '
b0010 *
1+
1/
01
12
15
16
#248000000
b1100 #
b0011 $
b1100 '
b0011 *
0+
0,
0/
11
02
04
05
16
07
19
0:
0;
#250000000
b1101 #
b0100 $
b1101 '
b0100 *
1+
1,
1/
01
12
15
06
17
1:
1;
#252000000
b1110 #
b0101 $
b1110 '
b0101 *
0+
0/
11
02
14
05
06
#254000000
b1111 #
b0110 $
b1111 '
b0110 *
1+
1/
01
12
15
16
#256000000
b1000 "
b0000 #
b1000 $
0%
b1000 &
b0000 '
0)
b1000 *
0+
0,
0-
0.
0/
02
03
04
05
06
07
08
09
0:
0;
0<
1=
0>
0?
1@
0A
#258000000
b0001 #
b1001 $
b0001 '
b1001 *
1/
11
#260000000
b0010 #
b1010 $
b0010 '
b1010 *
0/
01
14
16
#262000000
b0011 #
b1011 $
b0011 '
b1011 *
1/
11
#264000000
b0100 #
b1100 $
b0100 '
b1100 *
0/
01
04
06
19
1;
#266000000
b0101 #
b1101 $
b0101 '
b1101 *
1/
11
#268000000
b0110 #
b1110 $
b0110 '
b1110 *
0/
01
14
16
#270000000
b0111 #
b1111 $
b0111 '
b1111 *
1/
11
#272000000
b1000 #
b0000 $
1%
b1000 '
1)
b0000 *
0/
01
04
06
09
0;
1>
0@
1A
#274000000
b1001 #
b0001 $
b1001 '
b0001 *
1/
11
#276000000
b1010 #
b0010 $
b1010 '
b0010 *
0/
01
14
16
#278000000
b1011 #
b0011 $
b1011 '
b0011 *
1/
11
#280000000
b1100 #
b0100 $
b1100 '
b0100 *
0/
01
04
06
19
1;
#282000000
b1101 #
b0101 $
b1101 '
b0101 *
1/
11
#284000000
b1110 #
b0110 $
b1110 '
b0110 *
0/
01
14
16
#286000000
b1111 #
b0111 $
b1111 '
b0111 *
1/
11
#288000000
b1001 "
b0000 #
b1001 $
0%
b1001 &
b0000 '
0)
b1001 *
1.
0/
04
06
09
0;
0>
1@
0A
#290000000
b0001 #
b1010 $
b0001 '
b1010 *
1+
1/
01
12
15
16
#292000000
b0010 #
b1011 $
b0010 '
b1011 *
0+
0,
0/
11
02
14
05
16
07
0:
0;
#294000000
b0011 #
b1100 $
b0011 '
b1100 *
1+
1,
1/
01
12
15
06
17
1:
1;
#296000000
b0100 #
b1101 $
0%
b0100 '
0)
b1101 *
0+
0,
0-
0/
11
02
04
05
06
07
19
0:
1;
0<
0?
1@
0A
#298000000
b0101 #
b1110 $
b0101 '
b1110 *
1+
1/
01
12
15
16
#300000000
b0110 #
b1111 $
0%
b0110 '
0)
b1111 *
0+
0,
0-
0/
11
02
14
05
16
07
0:
1;
0<
0?
1@
0A
#302000000
b0111 #
b0000 $
1%
b0111 '
1)
b0000 *
1+
1,
1-
1/
01
12
15
06
17
1:
0;
1<
1?
0@
1A
#304000000
b1000 #
b0001 $
b1000 '
b0001 *
0+
0,
0-
0/
11
02
04
05
06
07
09
0:
0;
0<
1>
0?
0@
#306000000
b1001 #
b0010 $
b1001 '
b0010 *
1+
1/
01
12
15
16
#308000000
b1010 #
b0011 $
b1010 '
b0011 *
0+
0,
0/
11
02
14
05
16
07
0:
0;
#310000000
b1011 #
b0100 $
b1011 '
b0100 *
1+
1,
1/
01
12
15
06
17
1:
1;
#312000000
b1100 #
b0101 $
b1100 '
b0101 *
0+
0,
0-
0/
11
02
04
05
06
07
19
0:
1;
0<
0?
0@
#314000000
b1101 #
b0110 $
b1101 '
b0110 *
1+
1/
01
12
15
16
#316000000
b1110 #
b0111 $
b1110 '
b0111 *
0+
0,
0-
0/
11
02
14
05
16
07
0:
1;
0<
0?
0@
#318000000
b1111 #
b1000 $
b1111 '
b1000 *
1+
1,
1-
1/
01
12
15
06
17
1:
0;
1<
1?
1@
#320000000
b1010 "
b0000 #
b1010 $
0%
b1010 &
b0000 '
0)
b1010 *
0+
0,
0-
0.
0/
02
13
04
05
16
07
09
0:
0;
0<
0>
0?
1@
0A
#322000000
b0001 #
b1011 $
b0001 '
b1011 *
1/
11
#324000000
b0010 #
b1100 $
b0010 '
b1100 *
1,
0/
01
14
06
17
1:
1;
#326000000
b0011 #
b1101 $
b0011 '
b1101 *
1/
11
#328000000
b0100 #
b1110 $
0%
b0100 '
0)
b1110 *
0,
0-
0/
01
04
16
07
19
0:
1;
0<
0?
1@
0A
#330000000
b0101 #
b1111 $
b0101 '
b1111 *
1/
11
#332000000
b0110 #
b0000 $
1%
b0110 '
1)
b0000 *
1,
1-
0/
01
14
06
17
1:
0;
1<
1?
0@
1A
#334000000
b0111 #
b0001 $
b0111 '
b0001 *
1/
11
#336000000
b1000 #
b0010 $
b1000 '
b0010 *
0,
0-
0/
01
04
16
07
09
0:
0;
0<
1>
0?
0@
#338000000
b1001 #
b0011 $
b1001 '
b0011 *
1/
11
#340000000
b1010 #
b0100 $
b1010 '
b0100 *
1,
0/
01
14
06
17
1:
1;
#342000000
b1011 #
b0101 $
b1011 '
b0101 *
1/
11
#344000000
b1100 #
b0110 $
b1100 '
b0110 *
0,
0-
0/
01
04
16
07
19
0:
1;
0<
0?
0@
#346000000
b1101 #
b0111 $
b1101 '
b0111 *
1/
11
#348000000
b1110 #
b1000 $
b1110 '
b1000 *
1,
1-
0/
01
14
06
17
1:
0;
1<
1?
1@
#350000000
b1111 #
b1001 $
b1111 '
b1001 *
1/
11
#352000000
b1011 "
b0000 #
b1011 $
0%
b1011 &
b0000 '
0)
b1011 *
0,
0-
1.
0/
04
16
07
09
0:
0;
0<
0>
0?
1@
0A
#354000000
b0001 #
b1100 $
b0001 '
b1100 *
1+
1,
1/
01
12
15
06
17
1:
1;
#356000000
b0010 #
b1101 $
b0010 '
b1101 *
0+
0/
11
02
14
05
06
#358000000
b0011 #
b1110 $
b0011 '
b1110 *
1+
1/
01
12
15
16
#360000000
b0100 #
b1111 $
0%
b0100 '
0)
b1111 *
0+
0,
0-
0/
11
02
04
05
16
07
19
0:
1;
0<
0?
1@
0A
#362000000
b0101 #
b0000 $
1%
b0101 '
1)
b0000 *
1+
1,
1-
1/
01
12
15
06
17
1:
0;
1<
1?
0@
1A
#364000000
b0110 #
b0001 $
b0110 '
b0001 *
0+
0/
11
02
14
05
06
#366000000
b0111 #
b0010 $
b0111 '
b0010 *
1+
1/
01
12
15
16
#368000000
b1000 #
b0011 $
b1000 '
b0011 *
0+
0,
0-
0/
11
02
04
05
16
07
09
0:
0;
0<
1>
0?
0@
#370000000
b1001 #
b0100 $
b1001 '
b0100 *
1+
1,
1/
01
12
15
06
17
1:
1;
#372000000
b1010 #
b0101 $
b1010 '
b0101 *
0+
0/
11
02
14
05
06
#374000000
b1011 #
b0110 $
b1011 '
b0110 *
1+
1/
01
12
15
16
#376000000
b1100 #
b0111 $
b1100 '
b0111 *
0+
0,
0-
0/
11
02
04
05
16
07
19
0:
1;
0<
0?
0@
#378000000
b1101 #
b1000 $
b1101 '
b1000 *
1+
1,
1-
1/
01
12
15
06
17
1:
0;
1<
1?
1@
#380000000
b1110 #
b1001 $
b1110 '
b1001 *
0+
0/
11
02
14
05
06
#382000000
b1111 #
b1010 $
b1111 '
b1010 *
1+
1/
01
12
15
16
#384000000
b1100 "
b0000 #
b1100 $
0%
b1100 &
b0000 '
0)
b1100 *
0+
0,
0-
0.
0/
02
03
04
05
06
07
18
09
0:
1;
0<
0>
0?
1@
0A
#386000000
b0001 #
b1101 $
b0001 '
b1101 *
1/
11
#388000000
b0010 #
b1110 $
b0010 '
b1110 *
0/
01
14
16
#390000000
b0011 #
b1111 $
b0011 '
b1111 *
1/
11
#392000000
b0100 #
b0000 $
1%
b0100 '
1)
b0000 *
1-
0/
01
04
06
19
0;
1<
1?
0@
1A
#394000000
b0101 #
b0001 $
b0101 '
b0001 *
1/
11
#396000000
b0110 #
b0010 $
b0110 '
b0010 *
0/
01
14
16
#398000000
b0111 #
b0011 $
b0111 '
b0011 *
1/
11
#400000000
b1000 #
b0100 $
b1000 '
b0100 *
0-
0/
01
04
06
09
1;
0<
1>
0?
0@
#402000000
b1001 #
b0101 $
b1001 '
b0101 *
1/
11
#404000000
b1010 #
b0110 $
b1010 '
b0110 *
0/
01
14
16
#406000000
b1011 #
b0111 $
b1011 '
b0111 *
1/
11
#408000000
b1100 #
b1000 $
b1100 '
b1000 *
1-
0/
01
04
06
19
0;
1<
1?
1@
#410000000
b1101 #
b1001 $
b1101 '
b1001 *
1/
11
#412000000
b1110 #
b1010 $
b1110 '
b1010 *
0/
01
14
16
#414000000
b1111 #
b1011 $
b1111 '
b1011 *
1/
11
#416000000
b1101 "
b0000 #
b1101 $
0%
b1101 &
b0000 '
0)
b1101 *
0-
1.
0/
04
06
09
1;
0<
0>
0?
1@
0A
#418000000
b0001 #
b1110 $
b0001 '
b1110 *
1+
1/
01
12
15
16
#420000000
b0010 #
b1111 $
0%
b0010 '
0)
b1111 *
0+
0,
0-
0/
11
02
14
05
16
07
0:
1;
0<
0?
1@
0A
#422000000
b0011 #
b0000 $
1%
b0011 '
1)
b0000 *
1+
1,
1-
1/
01
12
15
06
17
1:
0;
1<
1?
0@
1A
#424000000
b0100 #
b0001 $
b0100 '
b0001 *
0+
0,
0/
11
02
04
05
06
07
19
0:
0;
#426000000
b0101 #
b0010 $
b0101 '
b0010 *
1+
1/
01
12
15
16
#428000000
b0110 #
b0011 $
b0110 '
b0011 *
0+
0,
0/
11
02
14
05
16
07
0:
0;
#430000000
b0111 #
b0100 $
b0111 '
b0100 *
1+
1,
1/
01
12
15
06
17
1:
1;
#432000000
b1000 #
b0101 $
b1000 '
b0101 *
0+
0,
0-
0/
11
02
04
05
06
07
09
0:
1;
0<
1>
0?
0@
#434000000
b1001 #
b0110 $
b1001 '
b0110 *
1+
1/
01
12
15
16
#436000000
b1010 #
b0111 $
b1010 '
b0111 *
0+
0,
0-
0/
11
02
14
05
16
07
0:
1;
0<
0?
0@
#438000000
b1011 #
b1000 $
b1011 '
b1000 *
1+
1,
1-
1/
01
12
15
06
17
1:
0;
1<
1?
1@
#440000000
b1100 #
b1001 $
b1100 '
b1001 *
0+
0,
0/
11
02
04
05
06
07
19
0:
0;
#442000000
b1101 #
b1010 $
b1101 '
b1010 *
1+
1/
01
12
15
16
#444000000
b1110 #
b1011 $
b1110 '
b1011 *
0+
0,
0/
11
02
14
05
16
07
0:
0;
#446000000
b1111 #
b1100 $
b1111 '
b1100 *
1+
1,
1/
01
12
15
06
17
1:
1;
#448000000
b1110 "
b0000 #
b1110 $
0%
b1110 &
b0000 '
0)
b1110 *
0+
0,
0-
0.
0/
02
13
04
05
16
07
09
0:
1;
0<
0>
0?
1@
0A
#450000000
b0001 #
b1111 $
b0001 '
b1111 *
1/
11
#452000000
b0010 #
b0000 $
1%
b0010 '
1)
b0000 *
1,
1-
0/
01
14
06
17
1:
0;
1<
1?
0@
1A
#454000000
b0011 #
b0001 $
b0011 '
b0001 *
1/
11
#456000000
b0100 #
b0010 $
b0100 '
b0010 *
0,
0/
01
04
16
07
19
0:
0;
#458000000
b0101 #
b0011 $
b0101 '
b0011 *
1/
11
#460000000
b0110 #
b0100 $
b0110 '
b0100 *
1,
0/
01
14
06
17
1:
1;
#462000000
b0111 #
b0101 $
b0111 '
b0101 *
1/
11
#464000000
b1000 #
b0110 $
b1000 '
b0110 *
0,
0-
0/
01
04
16
07
09
0:
1;
0<
1>
0?
0@
#466000000
b1001 #
b0111 $
b1001 '
b0111 *
1/
11
#468000000
b1010 #
b1000 $
b1010 '
b1000 *
1,
1-
0/
01
14
06
17
1:
0;
1<
1?
1@
#470000000
b1011 #
b1001 $
b1011 '
b1001 *
1/
11
#472000000
b1100 #
b1010 $
b1100 '
b1010 *
0,
0/
01
04
16
07
19
0:
0;
#474000000
b1101 #
b1011 $
b1101 '
b1011 *
1/
11
#476000000
b1110 #
b1100 $
b1110 '
b1100 *
1,
0/
01
14
06
17
1:
1;
#478000000
b1111 #
b1101 $
b1111 '
b1101 *
1/
11
#480000000
b1111 "
b0000 #
b1111 $
0%
b1111 &
b0000 '
0)
b1111 *
0,
0-
1.
0/
04
16
07
09
0:
1;
0<
0>
0?
1@
0A
#482000000
b0001 #
b0000 $
1%
b0001 '
1)
b0000 *
1+
1,
1-
1/
01
12
15
06
17
1:
0;
1<
1?
0@
1A
#484000000
b0010 #
b0001 $
b0010 '
b0001 *
0+
0/
11
02
14
05
06
#486000000
b0011 #
b0010 $
b0011 '
b0010 *
1+
1/
01
12
15
16
#488000000
b0100 #
b0011 $
b0100 '
b0011 *
0+
0,
0/
11
02
04
05
16
07
19
0:
0;
#490000000
b0101 #
b0100 $
b0101 '
b0100 *
1+
1,
1/
01
12
15
06
17
1:
1;
#492000000
b0110 #
b0101 $
b0110 '
b0101 *
0+
0/
11
02
14
05
06
